<?xml version="1.0" encoding="utf-8" ?>
<dwsync>
<file name="author-info.php" server="ftp.mikehammari.com//public_html/wp-content/themes/" local="130361061140000000" remote="130500095400000000" />
<file name="backers.php" server="ftp.mikehammari.com//public_html/wp-content/themes/" local="130361061140000000" remote="130500095400000000" />
<file name="campaign-sort-tabs.php" server="ftp.mikehammari.com//public_html/wp-content/themes/" local="130361061140000000" remote="130500095400000000" />
<file name="meta.php" server="ftp.mikehammari.com//public_html/wp-content/themes/" local="130361061140000000" remote="130500095400000000" />
<file name="project-details.php" server="ftp.mikehammari.com//public_html/wp-content/themes/" local="130361061140000000" remote="130500095400000000" />
<file name="share.php" server="ftp.mikehammari.com//public_html/wp-content/themes/" local="130361061140000000" remote="130500095400000000" />
<file name="title.php" server="ftp.mikehammari.com//public_html/wp-content/themes/" local="130361061140000000" remote="130500095400000000" />
<file name="updates.php" server="ftp.mikehammari.com//public_html/wp-content/themes/" local="130361061140000000" remote="130500095400000000" />
</dwsync>